golem/__init__.py
golem/_version.py
golem/extensions.cpython-37m-darwin.so
golem/golem.py
golem/utils.py
matter_golem-1.0.dist-info/LICENSE
matter_golem-1.0.dist-info/METADATA
matter_golem-1.0.dist-info/WHEEL
matter_golem-1.0.dist-info/top_level.txt
matter_golem-1.0.dist-info/RECORD
