Metadata-Version: 2.1
Name: matter-golem
Version: 1.0
Summary: Golem: An Algorithm for Robust Experiment and Process Optimization
Home-page: https://github.com/aspuru-guzik-group/golem
Author: Matteo Aldeghi
Author-email: matteo.aldeghi@vectorinstitute.ai
License: MIT
Platform: UNKNOWN
Classifier: Development Status :: 3 - Alpha
Classifier: License :: OSI Approved :: MIT License
Classifier: Programming Language :: Python
Classifier: Intended Audience :: Science/Research
Classifier: Topic :: Scientific/Engineering
Requires-Python: >=3.7
Requires-Dist: numpy
Requires-Dist: scipy (>=1.4)
Requires-Dist: scikit-learn
Requires-Dist: pandas
